bisnet/__init__.py
bisnet/model.py
bisnet/resnet.py
bisnet-1.0.1.dist-info/LICENSE
bisnet-1.0.1.dist-info/METADATA
bisnet-1.0.1.dist-info/WHEEL
bisnet-1.0.1.dist-info/top_level.txt
bisnet-1.0.1.dist-info/RECORD
